gcsim_pypi/__init__.py
gcsim_pypi/aliases/__init__.py
gcsim_pypi/aliases/artifacts.py
gcsim_pypi/aliases/characters.py
gcsim_pypi/aliases/weapons.py
gcsim_pypi/availability/__init__.py
gcsim_pypi/availability/artifacts.py
gcsim_pypi/availability/characters.py
gcsim_pypi/availability/weapons.py
gcsim_pypi/bin/gcsim
gcsim_pypi/bin/gcsim.arm64
gcsim_pypi/bin/gcsim.darwin
gcsim_pypi/bin/gcsim.darwin.arm64
gcsim_pypi/bin/gcsim.exe
gcsim_pypi-2.39.0.dist-info/METADATA
gcsim_pypi-2.39.0.dist-info/WHEEL
gcsim_pypi-2.39.0.dist-info/licenses/LICENSE
gcsim_pypi-2.39.0.dist-info/RECORD
